gitlab_logging
