Metadata-Version: 1.1
Name: django-gitlab-logging
Version: 0.2.1
Summary: A logging handler that opens GitLab issues on server error.
Home-page: https://github.com/valeriansaliou/django-gitlab-logging
Author: Valérian Saliou
Author-email: valerian@valeriansaliou.name
License: MIT - http://opensource.org/licenses/mit-license.php
Platform: UNKNOWN
Classifier: Development Status :: 3 - Alpha
Classifier: Environment :: Web Environment
Classifier: Framework :: Django
Classifier: Intended Audience :: Developers
Classifier: Natural Language :: English
Classifier: Programming Language :: Python
